djheroku/__init__.py
djheroku/_version.py
djheroku/auth.py
djheroku/authpatch.py
djheroku/conf.py
djheroku/fixture.py
djheroku/middleware.py
djheroku/tests.py
Djheroku-0.6.1.dist-info/LICENSE.md
Djheroku-0.6.1.dist-info/METADATA
Djheroku-0.6.1.dist-info/WHEEL
Djheroku-0.6.1.dist-info/top_level.txt
Djheroku-0.6.1.dist-info/RECORD
