Metadata-Version: 2.1
Name: Djheroku
Version: 0.6.1
Summary: Some helper functionality for binding Heroku configuration to Django
Home-page: http://github.com/fubaz/djheroku/
Author: Ferrix Hovi
Author-email: ferrix+git@ferrix.fi
License: UNKNOWN
Platform: UNKNOWN
Classifier: Development Status :: 5 - Production/Stable
Classifier: Environment :: Web Environment
Classifier: Intended Audience :: Developers
Classifier: License :: OSI Approved :: MIT License
Classifier: Operating System :: OS Independent
Classifier: Programming Language :: Python
Classifier: Framework :: Django
Requires-Dist: Django (>=1.4.1)
